vllm_spyre/__init__.py
vllm_spyre/_version.py
vllm_spyre/compat_utils.py
vllm_spyre/compilation_utils.py
vllm_spyre/envs.py
vllm_spyre/perf_metrics.py
vllm_spyre/platform.py
vllm_spyre/utils.py
vllm_spyre/config/__init__.py
vllm_spyre/config/known_model_configs.json
vllm_spyre/config/runtime_config_validator.py
vllm_spyre/config/supported_configs.yaml
vllm_spyre/model_executor/__init__.py
vllm_spyre/model_executor/model_loader/__init__.py
vllm_spyre/model_executor/model_loader/spyre.py
vllm_spyre/model_executor/model_loader/spyre_setup.py
vllm_spyre/v1/__init__.py
vllm_spyre/v1/core/__init__.py
vllm_spyre/v1/core/scheduler.py
vllm_spyre/v1/metrics/__init__.py
vllm_spyre/v1/metrics/stats_logger.py
vllm_spyre/v1/sample/golden_token_injector.py
vllm_spyre/v1/sample/spyre_logits_processor.py
vllm_spyre/v1/worker/__init__.py
vllm_spyre/v1/worker/spyre_input_batch.py
vllm_spyre/v1/worker/spyre_model_runner.py
vllm_spyre/v1/worker/spyre_worker.py
vllm_spyre-1.4.3.dist-info/licenses/LICENSE
vllm_spyre-1.4.3.dist-info/METADATA
vllm_spyre-1.4.3.dist-info/WHEEL
vllm_spyre-1.4.3.dist-info/entry_points.txt
vllm_spyre-1.4.3.dist-info/top_level.txt
vllm_spyre-1.4.3.dist-info/RECORD
