Metadata-Version: 2.4
Name: vllm-spyre
Version: 1.4.3
Summary: vLLM plugin for Spyre hardware support
License: Apache 2
Requires-Python: >=3.11
License-File: LICENSE
Requires-Dist: fms-model-optimizer[fp8]>=0.8.0
Requires-Dist: ibm-fms<2.0,>=1.5.0
Requires-Dist: vllm<=0.12.0,>=0.10.2
Requires-Dist: pytest-mock>=3.15.0
Dynamic: license-file
